ligandsplitter/__init__.py
ligandsplitter/_version.py
ligandsplitter/basefunctions.py
ligandsplitter/ligandanalysis.py
ligandsplitter/ligandderive.py
ligandsplitter/ligandgenerate.py
ligandsplitter/ligandsplit.py
ligandsplitter/ligandvalidate.py
ligandsplitter/py.typed
ligandsplitter/tests/__init__.py
ligandsplitter/tests/test_ligandsplitter.py
ligandsplitter-0.0.4.dist-info/licenses/LICENSE
ligandsplitter-0.0.4.dist-info/METADATA
ligandsplitter-0.0.4.dist-info/WHEEL
ligandsplitter-0.0.4.dist-info/top_level.txt
ligandsplitter-0.0.4.dist-info/RECORD
