Metadata-Version: 2.4
Name: ligandsplitter
Version: 0.0.4
Summary: A python package for splitting, creating, and validating ligand files
Author-email: Lee Schoneman <kes6022@rit.edu>
License: GPL-3.0-or-later
Project-URL: Source, https://github.com/leesch27/ligandsplitter/
Project-URL: Documentation, https://ligandsplitter.readthedocs.io/
Classifier: Programming Language :: Python :: 3
Requires-Python: >=3.8
License-File: LICENSE
Requires-Dist: numpy
Requires-Dist: pandas
Requires-Dist: rdkit
Requires-Dist: MDAnalysis
Requires-Dist: biopython
Requires-Dist: jupyter
Requires-Dist: scikit-learn
Requires-Dist: xgboost
Requires-Dist: rcsb-api
Provides-Extra: test
Requires-Dist: pytest>=6.1.2; extra == "test"
Dynamic: license-file
